coptic_converter/__init__.py
coptic_converter/coptic_converter.py
Rucopm_Conventer_Nopent-0.0.1.dist-info/LICENSE.txt
Rucopm_Conventer_Nopent-0.0.1.dist-info/METADATA
Rucopm_Conventer_Nopent-0.0.1.dist-info/WHEEL
Rucopm_Conventer_Nopent-0.0.1.dist-info/top_level.txt
Rucopm_Conventer_Nopent-0.0.1.dist-info/RECORD
